README.rst
setup.py
djdg_common_verify/Const.py
djdg_common_verify/__init__.py
djdg_common_verify/admin.py
djdg_common_verify/apps.py
djdg_common_verify/bankcard_auth.py
djdg_common_verify/exceptions.py
djdg_common_verify/idcard_auth.py
djdg_common_verify/models.py
djdg_common_verify/paypassword_auth.py
djdg_common_verify/rest_client.py
djdg_common_verify/serializers.py
djdg_common_verify/tests.py
djdg_common_verify/views.py
djdg_common_verify/migrations/0001_initial.py
djdg_common_verify/migrations/0002_auto_insert_bank_info_message.py
djdg_common_verify/migrations/__init__.py
djdg_common_verify/utils/__init__.py
djdg_common_verify/utils/cache.py
djdg_common_verify/utils/hailstone.py
djdg_python_common_verify_SDK.egg-info/PKG-INFO
djdg_python_common_verify_SDK.egg-info/SOURCES.txt
djdg_python_common_verify_SDK.egg-info/dependency_links.txt
djdg_python_common_verify_SDK.egg-info/not-zip-safe
djdg_python_common_verify_SDK.egg-info/requires.txt
djdg_python_common_verify_SDK.egg-info/top_level.txt