Metadata-Version: 1.1
Name: djdg-python-common-verify-SDK
Version: 0.0.6
Summary: djdg common verify
Home-page: https://pypi.python.org/pypi/djdg-common-verify
Author: fredzhang
Author-email: slzhang08@qq.com
License: BSD
Platform: UNKNOWN
Classifier: Development Status :: 3 - Alpha
Classifier: Programming Language :: Python :: 2
Classifier: Environment :: Web Environment
Classifier: Intended Audience :: Developers
Classifier: License :: OSI Approved :: BSD License
Classifier: Operating System :: OS Independent
Classifier: Framework :: Django
